{"/*":["X-Frame-Options: DENY","X-XSS-Protection: 1; mode=block","X-Content-Type-Options: nosniff","Referrer-Policy: same-origin"],"/styles.984b8fcd1038b38e49c3.css":["Cache-Control: public, max-age=31536000, immutable"],"/commons-65168afd334199732639.js":["Cache-Control: public, max-age=31536000, immutable"],"/component---src-components-post-template-tsx-7bb4b92fae6b5afb345b.js":["Cache-Control: public, max-age=31536000, immutable"],"/component---src-pages-404-tsx-07bda1b1a11cdb8728e4.js":["Cache-Control: public, max-age=31536000, immutable"],"/component---src-pages-about-tsx-0a1302a3d5c46dd7755a.js":["Cache-Control: public, max-age=31536000, immutable"],"/component---src-pages-categories-tsx-af0ce18237a2daca8014.js":["Cache-Control: public, max-age=31536000, immutable"],"/component---src-pages-index-tsx-85154875e72cadcc5e57.js":["Cache-Control: public, max-age=31536000, immutable"],"/webpack-runtime-b9015d0f91a954c59a6a.js":["Cache-Control: public, max-age=31536000, immutable"],"/framework-27f7b01b639722126502.js":["Cache-Control: public, max-age=31536000, immutable"],"/app-f79a4b8207b6cc72845e.js":["Cache-Control: public, max-age=31536000, immutable"],"/static/*":["Cache-Control: public, max-age=31536000, immutable"],"/sw.js":["Cache-Control: public, max-age=0, must-revalidate"],"/2021-03-17-React array key/":["Link: </webpack-runtime-b9015d0f91a954c59a6a.js>; rel=preload; as=script; nopush","Link: </framework-27f7b01b639722126502.js>; rel=preload; as=script; nopush","Link: </app-f79a4b8207b6cc72845e.js>; rel=preload; as=script; nopush","Link: </commons-65168afd334199732639.js>; rel=preload; as=script; nopush","Link: </component---src-components-post-template-tsx-7bb4b92fae6b5afb345b.js>; rel=preload; as=script; nopush","Link: </page-data/app-data.json>; rel=preload; as=fetch; crossorigin; nopush","Link: </page-data/2021-03-17-React array key/page-data.json>; rel=preload; as=fetch; crossorigin; nopush"],"/2021-05-31-Git modify commit Username/":["Link: </webpack-runtime-b9015d0f91a954c59a6a.js>; rel=preload; as=script; nopush","Link: </framework-27f7b01b639722126502.js>; rel=preload; as=script; nopush","Link: </app-f79a4b8207b6cc72845e.js>; rel=preload; as=script; nopush","Link: </commons-65168afd334199732639.js>; rel=preload; as=script; nopush","Link: </component---src-components-post-template-tsx-7bb4b92fae6b5afb345b.js>; rel=preload; as=script; nopush","Link: </page-data/app-data.json>; rel=preload; as=fetch; crossorigin; nopush","Link: </page-data/2021-05-31-Git modify commit Username/page-data.json>; rel=preload; as=fetch; crossorigin; nopush"],"/2021-03-19-reactLifeCycle/":["Link: </webpack-runtime-b9015d0f91a954c59a6a.js>; rel=preload; as=script; nopush","Link: </framework-27f7b01b639722126502.js>; rel=preload; as=script; nopush","Link: </app-f79a4b8207b6cc72845e.js>; rel=preload; as=script; nopush","Link: </commons-65168afd334199732639.js>; rel=preload; as=script; nopush","Link: </component---src-components-post-template-tsx-7bb4b92fae6b5afb345b.js>; rel=preload; as=script; nopush","Link: </page-data/app-data.json>; rel=preload; as=fetch; crossorigin; nopush","Link: </page-data/2021-03-19-reactLifeCycle/page-data.json>; rel=preload; as=fetch; crossorigin; nopush"],"/2021-06-25-Programers JavascriptStudy/":["Link: </webpack-runtime-b9015d0f91a954c59a6a.js>; rel=preload; as=script; nopush","Link: </framework-27f7b01b639722126502.js>; rel=preload; as=script; nopush","Link: </app-f79a4b8207b6cc72845e.js>; rel=preload; as=script; nopush","Link: </commons-65168afd334199732639.js>; rel=preload; as=script; nopush","Link: </component---src-components-post-template-tsx-7bb4b92fae6b5afb345b.js>; rel=preload; as=script; nopush","Link: </page-data/app-data.json>; rel=preload; as=fetch; crossorigin; nopush","Link: </page-data/2021-06-25-Programers JavascriptStudy/page-data.json>; rel=preload; as=fetch; crossorigin; nopush"],"/2021-09-13-CentOS에서 Nginx 로 REACT배포/":["Link: </webpack-runtime-b9015d0f91a954c59a6a.js>; rel=preload; as=script; nopush","Link: </framework-27f7b01b639722126502.js>; rel=preload; as=script; nopush","Link: </app-f79a4b8207b6cc72845e.js>; rel=preload; as=script; nopush","Link: </commons-65168afd334199732639.js>; rel=preload; as=script; nopush","Link: </component---src-components-post-template-tsx-7bb4b92fae6b5afb345b.js>; rel=preload; as=script; nopush","Link: </page-data/app-data.json>; rel=preload; as=fetch; crossorigin; nopush","Link: </page-data/2021-09-13-CentOS에서 Nginx 로 REACT배포/page-data.json>; rel=preload; as=fetch; crossorigin; nopush"],"/2021-09-27-API 디자인 가이드 참고 문서/":["Link: </webpack-runtime-b9015d0f91a954c59a6a.js>; rel=preload; as=script; nopush","Link: </framework-27f7b01b639722126502.js>; rel=preload; as=script; nopush","Link: </app-f79a4b8207b6cc72845e.js>; rel=preload; as=script; nopush","Link: </commons-65168afd334199732639.js>; rel=preload; as=script; nopush","Link: </component---src-components-post-template-tsx-7bb4b92fae6b5afb345b.js>; rel=preload; as=script; nopush","Link: </page-data/app-data.json>; rel=preload; as=fetch; crossorigin; nopush","Link: </page-data/2021-09-27-API 디자인 가이드 참고 문서/page-data.json>; rel=preload; as=fetch; crossorigin; nopush"],"/2021-10-28-자바스크립트의 this/":["Link: </webpack-runtime-b9015d0f91a954c59a6a.js>; rel=preload; as=script; nopush","Link: </framework-27f7b01b639722126502.js>; rel=preload; as=script; nopush","Link: </app-f79a4b8207b6cc72845e.js>; rel=preload; as=script; nopush","Link: </commons-65168afd334199732639.js>; rel=preload; as=script; nopush","Link: </component---src-components-post-template-tsx-7bb4b92fae6b5afb345b.js>; rel=preload; as=script; nopush","Link: </page-data/app-data.json>; rel=preload; as=fetch; crossorigin; nopush","Link: </page-data/2021-10-28-자바스크립트의 this/page-data.json>; rel=preload; as=fetch; crossorigin; nopush"],"/2021-10-29-자바스크립트의 this 2/":["Link: </webpack-runtime-b9015d0f91a954c59a6a.js>; rel=preload; as=script; nopush","Link: </framework-27f7b01b639722126502.js>; rel=preload; as=script; nopush","Link: </app-f79a4b8207b6cc72845e.js>; rel=preload; as=script; nopush","Link: </commons-65168afd334199732639.js>; rel=preload; as=script; nopush","Link: </component---src-components-post-template-tsx-7bb4b92fae6b5afb345b.js>; rel=preload; as=script; nopush","Link: </page-data/app-data.json>; rel=preload; as=fetch; crossorigin; nopush","Link: </page-data/2021-10-29-자바스크립트의 this 2/page-data.json>; rel=preload; as=fetch; crossorigin; nopush"],"/2021-11-25-Supported Browsers and Features/":["Link: </webpack-runtime-b9015d0f91a954c59a6a.js>; rel=preload; as=script; nopush","Link: </framework-27f7b01b639722126502.js>; rel=preload; as=script; nopush","Link: </app-f79a4b8207b6cc72845e.js>; rel=preload; as=script; nopush","Link: </commons-65168afd334199732639.js>; rel=preload; as=script; nopush","Link: </component---src-components-post-template-tsx-7bb4b92fae6b5afb345b.js>; rel=preload; as=script; nopush","Link: </page-data/app-data.json>; rel=preload; as=fetch; crossorigin; nopush","Link: </page-data/2021-11-25-Supported Browsers and Features/page-data.json>; rel=preload; as=fetch; crossorigin; nopush"],"/2021-12-08-Nextjs-page-prerender/":["Link: </webpack-runtime-b9015d0f91a954c59a6a.js>; rel=preload; as=script; nopush","Link: </framework-27f7b01b639722126502.js>; rel=preload; as=script; nopush","Link: </app-f79a4b8207b6cc72845e.js>; rel=preload; as=script; nopush","Link: </commons-65168afd334199732639.js>; rel=preload; as=script; nopush","Link: </component---src-components-post-template-tsx-7bb4b92fae6b5afb345b.js>; rel=preload; as=script; nopush","Link: </page-data/app-data.json>; rel=preload; as=fetch; crossorigin; nopush","Link: </page-data/2021-12-08-Nextjs-page-prerender/page-data.json>; rel=preload; as=fetch; crossorigin; nopush"],"/404/":["Link: </webpack-runtime-b9015d0f91a954c59a6a.js>; rel=preload; as=script; nopush","Link: </framework-27f7b01b639722126502.js>; rel=preload; as=script; nopush","Link: </app-f79a4b8207b6cc72845e.js>; rel=preload; as=script; nopush","Link: </commons-65168afd334199732639.js>; rel=preload; as=script; nopush","Link: </component---src-pages-404-tsx-07bda1b1a11cdb8728e4.js>; rel=preload; as=script; nopush","Link: </page-data/app-data.json>; rel=preload; as=fetch; crossorigin; nopush","Link: </page-data/404/page-data.json>; rel=preload; as=fetch; crossorigin; nopush"],"/404.html":["Link: </webpack-runtime-b9015d0f91a954c59a6a.js>; rel=preload; as=script; nopush","Link: </framework-27f7b01b639722126502.js>; rel=preload; as=script; nopush","Link: </app-f79a4b8207b6cc72845e.js>; rel=preload; as=script; nopush","Link: </commons-65168afd334199732639.js>; rel=preload; as=script; nopush","Link: </component---src-pages-404-tsx-07bda1b1a11cdb8728e4.js>; rel=preload; as=script; nopush","Link: </page-data/app-data.json>; rel=preload; as=fetch; crossorigin; nopush","Link: </page-data/404.html/page-data.json>; rel=preload; as=fetch; crossorigin; nopush"],"/about/":["Link: </webpack-runtime-b9015d0f91a954c59a6a.js>; rel=preload; as=script; nopush","Link: </framework-27f7b01b639722126502.js>; rel=preload; as=script; nopush","Link: </app-f79a4b8207b6cc72845e.js>; rel=preload; as=script; nopush","Link: </commons-65168afd334199732639.js>; rel=preload; as=script; nopush","Link: </component---src-pages-about-tsx-0a1302a3d5c46dd7755a.js>; rel=preload; as=script; nopush","Link: </page-data/app-data.json>; rel=preload; as=fetch; crossorigin; nopush","Link: </page-data/about/page-data.json>; rel=preload; as=fetch; crossorigin; nopush"],"/categories/":["Link: </webpack-runtime-b9015d0f91a954c59a6a.js>; rel=preload; as=script; nopush","Link: </framework-27f7b01b639722126502.js>; rel=preload; as=script; nopush","Link: </app-f79a4b8207b6cc72845e.js>; rel=preload; as=script; nopush","Link: </commons-65168afd334199732639.js>; rel=preload; as=script; nopush","Link: </component---src-pages-categories-tsx-af0ce18237a2daca8014.js>; rel=preload; as=script; nopush","Link: </page-data/app-data.json>; rel=preload; as=fetch; crossorigin; nopush","Link: </page-data/categories/page-data.json>; rel=preload; as=fetch; crossorigin; nopush"],"/":["Link: </webpack-runtime-b9015d0f91a954c59a6a.js>; rel=preload; as=script; nopush","Link: </framework-27f7b01b639722126502.js>; rel=preload; as=script; nopush","Link: </app-f79a4b8207b6cc72845e.js>; rel=preload; as=script; nopush","Link: </commons-65168afd334199732639.js>; rel=preload; as=script; nopush","Link: </component---src-pages-index-tsx-85154875e72cadcc5e57.js>; rel=preload; as=script; nopush","Link: </page-data/app-data.json>; rel=preload; as=fetch; crossorigin; nopush","Link: </page-data/index/page-data.json>; rel=preload; as=fetch; crossorigin; nopush"]}